LICENSE
MANIFEST.in
README.md
requirements.txt
setup.py
braidacq_exec.egg-info/PKG-INFO
braidacq_exec.egg-info/SOURCES.txt
braidacq_exec.egg-info/dependency_links.txt
braidacq_exec.egg-info/entry_points.txt
braidacq_exec.egg-info/requires.txt
braidacq_exec.egg-info/top_level.txt
braidpy/__init__.py
braidpy/__main__.py
braidpy/attention.py
braidpy/braid.py
braidpy/color.py
braidpy/detect_errors.py
braidpy/expe.py
braidpy/lexical.py
braidpy/lexicon.py
braidpy/modality.py
braidpy/percept.py
braidpy/semantic.py
braidpy/sensor.py
braidpy/simu.py
braidpy/utilities.py
braidpy/word.py
braidpy/resources/chardicts/alphabet_en.csv
braidpy/resources/chardicts/alphabet_fr_simplified.csv
braidpy/resources/chardicts/alphabet_ge.csv
braidpy/resources/chardicts/alphabet_lat.csv
braidpy/resources/chardicts/xsampa_ELP.csv
braidpy/resources/chardicts/xsampa_celex.csv
braidpy/resources/chardicts/xsampa_celex_german.csv
braidpy/resources/chardicts/xsampa_fr.csv
braidpy/resources/chardicts/xsampa_fr_simplified.csv
braidpy/resources/confusionMatrix/Simpson13Mod.csv
braidpy/resources/confusionMatrix/TownsendMod.csv
braidpy/resources/lexicon/ELP.csv
braidpy/resources/lexicon/celex_german.csv
braidpy/resources/lexicon/graphemic_segmentation_corrected_lexique_fr.csv
braidpy/resources/lexicon/lexicon_CDP.csv
braidpy/resources/lexicon/lexique_fr.csv