Metadata-Version: 2.1
Name: braidacq-exec
Version: 0.1.1
Summary: Toy version of Braid
Home-page: https://https://gitlab.com/braid-acq/BRAID-Acq
Author: Alexandra Steinhilber
Author-email: alexandra.st@free.fr
License: UNKNOWN
Platform: UNKNOWN
Classifier: Programming Language :: Python :: 3
Classifier: Operating System :: OS Independent
Requires-Python: >=3.8.5
